README.rst
setup.py
bin/ruledxml
bin/ruledxml-batched
ruledxml/__init__.py
ruledxml/core.py
ruledxml/decorators.py
ruledxml/exceptions.py
ruledxml/fs.py
ruledxml/xml.py
ruledxml.egg-info/PKG-INFO
ruledxml.egg-info/SOURCES.txt
ruledxml.egg-info/dependency_links.txt
ruledxml.egg-info/top_level.txt