Metadata-Version: 1.1
Name: ruledxml
Version: 1.4.0
Summary: Rule-based XML transformations
Home-page: http://lukas-prokop.at/proj/ruledxml/
Author: Lukas Prokop
Author-email: admin@lukas-prokop.at
License: BSD
Platform: any
Classifier: Development Status :: 4 - Beta
Classifier: Environment :: Console
Classifier: Intended Audience :: Developers
Classifier: Intended Audience :: Financial and Insurance Industry
Classifier: Intended Audience :: System Administrators
Classifier: License :: OSI Approved :: BSD License
Classifier: Natural Language :: English
Classifier: Operating System :: OS Independent
Classifier: Programming Language :: Python :: 3.4
Classifier: Topic :: Office/Business
Classifier: Topic :: Text Processing :: Markup :: XML
Requires: lxml (==3.4.4)
